hotedit/__init__.py
hotedit/editor.py
hotedit-0.9.1.post2.dist-info/LICENSE
hotedit-0.9.1.post2.dist-info/WHEEL
hotedit-0.9.1.post2.dist-info/METADATA
hotedit-0.9.1.post2.dist-info/RECORD
