Metadata-Version: 2.1
Name: hotedit
Version: 0.9.1.post2
Summary: Automatically find and launch an editor with a stream of text to edit; then save
Author: Cory Dodt
Author-email: 121705+corydodt@users.noreply.github.com
Requires-Python: >=3.6.2,<4
Classifier: Programming Language :: Python :: 3
Classifier: Programming Language :: Python :: 3.10
Classifier: Programming Language :: Python :: 3.7
Classifier: Programming Language :: Python :: 3.8
Classifier: Programming Language :: Python :: 3.9
Provides-Extra: test
Requires-Dist: pytest (>=6.2,<7.0); extra == "test"
Requires-Dist: pytest-cov (>=3.0.0,<4.0.0)
Requires-Dist: pytest-flakes (>=4.0.5,<5.0.0); extra == "test"
